setup.cfg
setup.py
PyBLEWrapper.egg-info/PKG-INFO
PyBLEWrapper.egg-info/SOURCES.txt
PyBLEWrapper.egg-info/dependency_links.txt
PyBLEWrapper.egg-info/requires.txt
PyBLEWrapper.egg-info/top_level.txt
pyble/__init__.py
pyble/_gatt.py
pyble/_roles.py
pyble/backend.py
pyble/handlers.py
pyble/patterns.py
pyble/utility.py
pyble/const/__init__.py
pyble/const/cycling_power_measurement.py
pyble/const/ln_control_point.py
pyble/const/location_and_speed.py
pyble/const/characteristic/__init__.py
pyble/const/characteristic/alert_category_id.py
pyble/const/characteristic/alert_category_id_bit_mask.py
pyble/const/characteristic/alert_level.py
pyble/const/characteristic/alert_notification_control_point.py
pyble/const/characteristic/alert_status.py
pyble/const/characteristic/battery_level.py
pyble/const/characteristic/blood_pressure_feature.py
pyble/const/characteristic/blood_pressure_measurement.py
pyble/const/characteristic/body_sensor_location.py
pyble/const/characteristic/boot_keyboard_inptut_report.py
pyble/const/characteristic/boot_keyboard_output_report.py
pyble/const/characteristic/boot_mouse_input_report.py
pyble/const/characteristic/csc_feature.py
pyble/const/characteristic/csc_measurement.py
pyble/const/characteristic/current_time.py
pyble/const/characteristic/cycling_power_control_point.py
pyble/const/characteristic/cycling_power_feature.py
pyble/const/characteristic/cycling_power_vector.py
pyble/const/characteristic/date_time.py
pyble/const/characteristic/day_date_time.py
pyble/const/characteristic/day_of_week.py
pyble/const/characteristic/device_name.py
pyble/const/characteristic/dst_offset.py
pyble/const/characteristic/exact_time_256.py
pyble/const/characteristic/firmware_revision_string.py
pyble/const/characteristic/glucose_feature.py
pyble/const/characteristic/glucose_measurement.py
pyble/const/characteristic/glucose_mesaurement_context.py
pyble/const/characteristic/hardware_revision_string.py
pyble/const/characteristic/heart_rate_control_point.py
pyble/const/characteristic/heart_rate_measurement.py
pyble/const/characteristic/hid_control_point.py
pyble/const/characteristic/hid_information.py
