Metadata-Version: 1.1
Name: PyBLEWrapper
Version: 0.2.6
Summary: Python Bluetooth Smart(BLE) manager wrapper for OSX
Home-page: https://github.com/brettchien/PyBLEWrapper
Author: Brett Chien
Author-email: brett.chien@gmail.com
License: MIT
Download-URL: https://github.com/brettchien/PyBLEWrapper/tarball/0.2.6
Keywords: Bluetooth Low Energy,BLE,OSX
Platform: UNKNOWN
